COPYING
Makefile
README
ez_setup.py
setup.cfg
setup.py
myword/__init__.py
myword/game.py
myword/myword.ico
myword/words.dat
pyword.egg-info/PKG-INFO
pyword.egg-info/SOURCES.txt
pyword.egg-info/dependency_links.txt
pyword.egg-info/entry_points.txt
pyword.egg-info/top_level.txt
win32/myword-install
win32/myword.bmp